xiwen/__about__.py
xiwen/__init__.py
xiwen/app.py
xiwen/interface.py
xiwen/assets/hanzi_pinyin_characters.tsv.txt
xiwen/assets/hsk30_hanzi.parquet
xiwen/utils/__init__.py
xiwen/utils/analyse.py
xiwen/utils/config.py
xiwen/utils/count.py
xiwen/utils/export.py
xiwen/utils/extract.py
xiwen/utils/hanzi.py
xiwen/utils/html.py
xiwen/utils/pinyin.py
xiwen/utils/transform.py
xiwen-0.2.1.dist-info/METADATA
xiwen-0.2.1.dist-info/WHEEL
xiwen-0.2.1.dist-info/licenses/LICENSE
xiwen-0.2.1.dist-info/RECORD
