Metadata-Version: 2.3
Name: xiwen
Version: 0.2.1
Summary: A tool to scan HTML for Chinese characters
Project-URL: documentation, https://github.com/essteer/xiwen/blob/main/README.md
Project-URL: repository, https://github.com/essteer/xiwen
Project-URL: issues, https://github.com/essteer/xiwen/issues
Author-email: Elliott Steer <essteer@pm.me>
License: MIT License
License-File: LICENSE
Keywords: CLI,Chinese,tool
Classifier: Development Status :: 4 - Beta
Classifier: Intended Audience :: Developers
Classifier: License :: OSI Approved :: MIT License
Classifier: Natural Language :: English
Classifier: Operating System :: OS Independent
Classifier: Programming Language :: Python :: 3
Classifier: Programming Language :: Python :: 3.10
Classifier: Programming Language :: Python :: 3.11
Classifier: Programming Language :: Python :: 3.12
Requires-Python: >=3.9
Requires-Dist: beautifulsoup4>=4.12.3
Requires-Dist: masquer>=1.1.1
Requires-Dist: polars==0.20.31
Requires-Dist: requests>=2.32.3
Provides-Extra: dev
Requires-Dist: hatch==1.11.1; extra == 'dev'
Requires-Dist: hatchling==1.24.2; extra == 'dev'
Requires-Dist: pre-commit==3.7.0; extra == 'dev'
Requires-Dist: ruff>=0.4.5; extra == 'dev'
